bids_derivatives/__init__.py
bids_derivatives/__main__.py
bids_derivatives/cli.py
bids_derivatives/dataset/__init__.py
bids_derivatives/dataset/dataset.py
bids_derivatives/dataset/messages.py
bids_derivatives/dataset/utils.py
bids_derivatives/derivative/__init__.py
bids_derivatives/derivative/derivative.py
bids_derivatives/derivative/messages.py
bids_derivatives/utils/__init__.py
bids_derivatives/utils/logs.py
bids_derivatives/utils/templates/__init__.py
bids_derivatives/utils/templates/bids.py
bids_derivatives-0.0.1.dist-info/LICENSE
bids_derivatives-0.0.1.dist-info/METADATA
bids_derivatives-0.0.1.dist-info/WHEEL
bids_derivatives-0.0.1.dist-info/top_level.txt
bids_derivatives-0.0.1.dist-info/RECORD
