Metadata-Version: 2.1
Name: bids-derivatives
Version: 0.0.1
Summary: Python package for querying BIDS Apps` processed derivatives.
Home-page: https://github.com/GalBenZvi/bids-derivatives
Author: Gal Ben-Zvi
Author-email: benzvigal@gmail.com
License: Apache-2.0
Project-URL: Source, https://github.com/GalBenZvi/bids-derivatives
Project-URL: Bug Reports, https://github.com/GalBenZvi/bids-derivatives/issues/
Keywords: mri,preprocessing,neuroscience,BIDS
Classifier: Development Status :: 5 - Production/Stable
Classifier: Intended Audience :: Science/Research
Classifier: Intended Audience :: Healthcare Industry
Classifier: License :: OSI Approved :: MIT License
Classifier: Operating System :: OS Independent
Classifier: Programming Language :: Python :: 3
Classifier: Programming Language :: Python :: 3.8
Classifier: Programming Language :: Python :: 3.9
Classifier: Programming Language :: Python :: 3.10
Classifier: Programming Language :: Python :: 3 :: Only
Requires-Python: <4,>=3.8
License-File: LICENSE
Requires-Dist: parse (~=1.19)
Provides-Extra: all
Requires-Dist: black (~=22.3) ; extra == 'all'
Requires-Dist: doc8 (~=0.10) ; extra == 'all'
Requires-Dist: flake8 (~=4.0) ; extra == 'all'
Requires-Dist: ipython ; extra == 'all'
Requires-Dist: isort (~=5.10) ; extra == 'all'
Requires-Dist: pre-commit ; extra == 'all'
Requires-Dist: pre-commit-hooks ; extra == 'all'
Requires-Dist: sphinx (~=4.5) ; extra == 'all'
Requires-Dist: sphinx-rtd-theme (~=1.0) ; extra == 'all'
Requires-Dist: coverage[toml] (>=6.2) ; extra == 'all'
Requires-Dist: pytest (~=7.1) ; extra == 'all'
Requires-Dist: tox (~=3.24) ; extra == 'all'
Requires-Dist: build ; extra == 'all'
Requires-Dist: twine ; extra == 'all'
Provides-Extra: dev
Requires-Dist: black (~=22.3) ; extra == 'dev'
Requires-Dist: doc8 (~=0.10) ; extra == 'dev'
Requires-Dist: flake8 (~=4.0) ; extra == 'dev'
Requires-Dist: ipython ; extra == 'dev'
Requires-Dist: isort (~=5.10) ; extra == 'dev'
Requires-Dist: pre-commit ; extra == 'dev'
Requires-Dist: pre-commit-hooks ; extra == 'dev'
Requires-Dist: sphinx (~=4.5) ; extra == 'dev'
Requires-Dist: sphinx-rtd-theme (~=1.0) ; extra == 'dev'
Requires-Dist: coverage[toml] (>=6.2) ; extra == 'dev'
Requires-Dist: pytest (~=7.1) ; extra == 'dev'
Requires-Dist: tox (~=3.24) ; extra == 'dev'
Provides-Extra: dist
Requires-Dist: build ; extra == 'dist'
Requires-Dist: twine ; extra == 'dist'
Provides-Extra: docs
Requires-Dist: sphinx (~=4.5) ; extra == 'docs'
Requires-Dist: sphinx-rtd-theme (~=1.0) ; extra == 'docs'
Provides-Extra: test
Requires-Dist: coverage[toml] (>=6.2) ; extra == 'test'
Requires-Dist: pytest (~=7.1) ; extra == 'test'
Requires-Dist: tox (~=3.24) ; extra == 'test'
